parallel.py
easy_parallel_py3-0.1.6.4.dist-info/LICENSE
easy_parallel_py3-0.1.6.4.dist-info/METADATA
easy_parallel_py3-0.1.6.4.dist-info/WHEEL
easy_parallel_py3-0.1.6.4.dist-info/top_level.txt
easy_parallel_py3-0.1.6.4.dist-info/RECORD
