Metadata-Version: 2.1
Name: easy-parallel-py3
Version: 0.1.6.4
Summary: Parallel wrapper for easy multi-threading (Python 3 version).
Home-page: https://github.com/amorehead/easy-parallel
Author: Raphael Townshend
Author-email: UNKNOWN
License: MIT
Platform: UNKNOWN
Requires-Dist: pathos
